bender/__init__.py
bender/data_explorer.py
bender/data_exporter/__init__.py
bender/data_exporter/disk.py
bender/data_exporter/interface.py
bender/data_exporter/pipeline.py
bender/data_importer/__init__.py
bender/data_importer/importer.py
bender/data_importer/interface.py
bender/data_importer/local_csv.py
bender/data_importer/tests/test_append_importer.py
bender/data_importer/tests/test_cached_importer.py
bender/evaluator/__init__.py
bender/evaluator/confusion_matrix.py
bender/evaluator/difference_distribution.py
bender/evaluator/factory_method.py
bender/evaluator/feature_importance.py
bender/evaluator/interface.py
bender/evaluator/precision_recall.py
bender/evaluator/predict_probability.py
bender/evaluator/roc.py
bender/evaluators.py
bender/explorer/__init__.py
bender/explorer/correlation.py
bender/explorer/factory.py
bender/explorer/histogram.py
bender/explorer/interface.py
bender/explorer/pair.py
bender/explorer/scatter.py
bender/explorer/tests/test_explorer.py
bender/explorer/violin.py
bender/explorers.py
bender/exporter/exporter.py
bender/importers.py
bender/metric/__init__.py
bender/metric/factory.py
bender/metric/interface.py
bender/metric/log_loss.py
bender/metric/mean_absolute_error.py
bender/metric/mean_absolute_percentage_error.py
bender/metric/mean_square_error.py
bender/metric/tests/test_metric_pipeline.py
bender/metrics.py
bender/model_exporter/__init__.py
bender/model_exporter/aws_s3_exporter.py
bender/model_exporter/disk_exporter.py
bender/model_exporter/factory.py
bender/model_exporter/interface.py
bender/model_exporter/tests/test_export_model.py
bender/model_exporters.py
bender/model_loader/model_loader.py
bender/model_loaders.py
bender/model_trainer/__init__.py
bender/model_trainer/decision_tree.py
bender/model_trainer/interface.py
bender/model_trainer/kneighbors.py
bender/model_trainer/linear_regression.py
bender/model_trainer/support_vector.py
bender/model_trainer/tests/test_regression_model.py
bender/model_trainer/tests/test_train_pipeline.py
benderml-0.1.19.dist-info/LICENSE
benderml-0.1.19.dist-info/WHEEL
benderml-0.1.19.dist-info/METADATA
benderml-0.1.19.dist-info/RECORD
