Metadata-Version: 2.1
Name: benderml
Version: 0.1.19
Summary: A Python package that makes ML processes easier, faster and less error prone
Home-page: https://github.com/otovo/bender
License: Apache-2.0
Keywords: python,typed,ml,prediction
Author: Mats E. Mollestad
Author-email: mats@mollestad.no
Requires-Python: >=3.9.7,<4.0.0
Classifier: Development Status :: 3 - Alpha
Classifier: Environment :: Web Environment
Classifier: Intended Audience :: Developers
Classifier: License :: OSI Approved :: Apache Software License
Classifier: Operating System :: OS Independent
Classifier: Programming Language :: Python
Classifier: Programming Language :: Python :: 3
Classifier: Programming Language :: Python :: 3.10
Classifier: Programming Language :: Python :: 3.6
Classifier: Programming Language :: Python :: 3.7
Classifier: Programming Language :: Python :: 3.8
Classifier: Programming Language :: Python :: 3.9
Classifier: Topic :: Internet :: WWW/HTTP
Classifier: Topic :: Internet :: WWW/HTTP :: Dynamic Content
Classifier: Topic :: Scientific/Engineering :: Artificial Intelligence
Classifier: Topic :: Software Development
Classifier: Topic :: Software Development :: Libraries
Classifier: Topic :: Software Development :: Libraries :: Application Frameworks
Classifier: Topic :: Software Development :: Libraries :: Python Modules
Requires-Dist: aioaws (>=0.12,<0.13)
Requires-Dist: asyncpg (>=0.24.0,<0.25.0)
Requires-Dist: databases (>=0.5.3,<0.6.0)
Requires-Dist: matplotlib (>=3.4.3,<4.0.0)
Requires-Dist: pandas (>=1.3.4,<2.0.0)
Requires-Dist: seaborn (>=0.11.2,<0.12.0)
Requires-Dist: sklearn (>=0.0,<0.1)
Requires-Dist: xgboost (>=1.5.0,<2.0.0)
Project-URL: Repository, https://github.com/otovo/bender
